{
    "name": "animateTo",
    "title": "jQuery animateTo",
    "description": "jQuery animate element to XY[] points.",
    "keywords": [
        "animate",
        "animation"
    ],
    "version": "1.0.0",
    "author": {
        "name": "Mohsen Sharify",
        "url": "http://mohsen.sharify.ir"
    },
    "maintainers": [
        {
            "name": "Mohsen Sharify",
            "email": "mohsen@sharify.ir",
            "url": "http://sharify.ir"
        }
    ],
    "licenses": [
        {
            "type": "MIT",
            "url": "https://github.com/mohsen-sharify/animateTo/blob/master/LICENSE.txt"
        }
    ],
    "bugs": "http://blog.sharify.ir/?p=223",
    "homepage": "http://blog.sharify.ir/?p=223",
    "docs": "http://blog.sharify.ir/?p=223",
    "download": "http://blog.sharify.ir/wp-content/uploads/2013/03/animateTo.jquery.js",
    "dependencies": {
        "jquery": ">=1.0"
    }
}
